[{"d":"2026-07-08","s":"run","m":48.8,"dist":4.12,"t":"Zwift - Lutece Express Run in Paris"},{"d":"2026-07-07","s":"bike","m":57.1,"dist":9.74,"t":"Zwift - Mayan 8 in Watopia"},{"d":"2026-07-06","s":"run","m":27.8,"dist":2.46,"t":"Zwift - Two Bridges Loop in Watopia"},{"d":"2026-07-05","s":"swim","m":42.8,"dist":1700.0,"t":"Pool Swim"},{"d":"2026-07-05","s":"bike","m":55.9,"dist":13.67,"t":"Zwift - Flat Out Fast in Watopia"},{"d":"2026-07-03","s":"swim","m":13.5,"dist":600.0,"t":"Pool Swim"},{"d":"2026-07-03","s":"run","m":39.7,"dist":3.62,"t":"Treadmill Running"},{"d":"2026-06-30","s":"run","m":35.1,"dist":3.05,"t":"Zwift - The PRL Full in London"},{"d":"2026-06-29","s":"bike","m":33.3,"dist":7.56,"t":"Zwift - Mend"},{"d":"2026-06-28","s":"run","m":53.2,"dist":4.11,"t":"Bridgewater Running"},{"d":"2026-06-18","s":"run","m":37.4,"dist":3.29,"t":"Zwift - Chili Pepper in Watopia"},{"d":"2026-06-17","s":"run","m":26.9,"dist":2.36,"t":"Zwift - Turf N Surf in Makuri Islands"},{"d":"2026-06-16","s":"run","m":18.6,"dist":1.65,"t":"Zwift - Fine and Sandy in Makuri Islands"},{"d":"2026-06-08","s":"run","m":43.0,"dist":4.03,"t":"Zwift - Surfin  Safari in Watopia"},{"d":"2026-06-06","s":"run","m":96.9,"dist":7.6,"t":"Bridgewater - W8 Sat Long Run - 6.5mi Lo"},{"d":"2026-06-02","s":"run","m":32.8,"dist":2.92,"t":"Zwift - Surfin  Safari in Watopia"},{"d":"2026-05-31","s":"run","m":93.2,"dist":7.68,"t":"Bridgewater Running"},{"d":"2026-05-28","s":"run","m":26.8,"dist":2.38,"t":"Zwift - Two Bridges Loop in Watopia"},{"d":"2026-05-27","s":"run","m":20.1,"dist":1.91,"t":"Zwift - Hill   Tempo #3"},{"d":"2026-05-26","s":"run","m":35.7,"dist":3.21,"t":"Zwift - Bridges and Boardwalks in Makuri"},{"d":"2026-05-24","s":"run","m":27.0,"dist":2.53,"t":"W6 Sun Easy Run #2 - 3mi Easy Ru"},{"d":"2026-05-22","s":"run","m":33.7,"dist":3.01,"t":"Zwift - Track Meet in Watopia"},{"d":"2026-05-21","s":"run","m":29.1,"dist":2.78,"t":"Zwift - Splash and Dash in Watopia"},{"d":"2026-05-20","s":"run","m":29.2,"dist":2.59,"t":"Zwift - 4.2mi Broken 600s"},{"d":"2026-05-19","s":"run","m":24.4,"dist":2.14,"t":"Zwift - 5K Loop in Watopia"},{"d":"2026-05-18","s":"run","m":25.2,"dist":2.64,"t":"Zwift - Zwift Academy Tri: Run Workout 3"},{"d":"2026-05-16","s":"run","m":62.8,"dist":5.07,"t":"Bridgewater - W5 Sat Long Run - 6mi Bloc"},{"d":"2026-05-15","s":"run","m":39.8,"dist":3.51,"t":"Zwift - Prospect Park Loop Run in New Yo"},{"d":"2026-05-14","s":"run","m":45.7,"dist":3.88,"t":"Zwift - Fartlek 5 s"},{"d":"2026-05-12","s":"run","m":34.7,"dist":3.14,"t":"Zwift - Valley to Mountaintop in Makuri "},{"d":"2026-05-11","s":"run","m":25.2,"dist":2.21,"t":"Zwift - 5K Loop in Watopia"},{"d":"2026-05-10","s":"run","m":24.9,"dist":2.33,"t":"Zwift - Splash and Dash in Watopia"},{"d":"2026-05-03","s":"run","m":25.4,"dist":2.52,"t":"W3 Sun Easy Run #2 - 2.5mi Easy"},{"d":"2026-05-02","s":"run","m":61.2,"dist":5.23,"t":"Bridgewater - Long Run"},{"d":"2026-04-27","s":"run","m":30.5,"dist":3.01,"t":"Zwift - Runna Session 3-7 Intervals"},{"d":"2026-04-26","s":"run","m":30.5,"dist":3.01,"t":"W2 Sun Easy Run #2 - 3mi Easy Ru"},{"d":"2026-04-25","s":"run","m":66.8,"dist":5.64,"t":"Bridgewater - W2 Sat Long Run - 5mi Prog"},{"d":"2026-04-20","s":"run","m":26.6,"dist":2.51,"t":"Zwift - Classique in London"},{"d":"2026-04-19","s":"run","m":29.2,"dist":2.51,"t":"Zwift - Duchy Estate in Yorkshire"},{"d":"2026-04-18","s":"run","m":44.5,"dist":4.64,"t":"Zwift - Surfin  Safari in Watopia"},{"d":"2026-04-17","s":"run","m":31.4,"dist":3.13,"t":"Zwift - Island Outskirts in Makuri Islan"},{"d":"2026-04-16","s":"run","m":33.2,"dist":3.27,"t":"Zwift - Three Village Loop in Makuri Isl"},{"d":"2026-04-11","s":"run","m":49.1,"dist":5.01,"t":"Zwift - Chili Pepper in Watopia"},{"d":"2026-04-10","s":"run","m":43.1,"dist":4.32,"t":"Zwift - Chili Pepper in Watopia"},{"d":"2026-04-08","s":"run","m":48.5,"dist":5.01,"t":"Zwift - Chili Pepper in Watopia"},{"d":"2026-04-07","s":"run","m":36.2,"dist":3.29,"t":"Zwift - Splash and Dash in Watopia"},{"d":"2026-04-04","s":"run","m":61.5,"dist":39020.0,"t":"Track Running"},{"d":"2026-03-31","s":"run","m":32.3,"dist":10760.0,"t":"Track Running"},{"d":"2026-03-30","s":"run","m":41.0,"dist":9.29,"t":"Running"},{"d":"2026-03-19","s":"run","m":35.1,"dist":3.03,"t":"Zwift - Bridges and Boardwalks in Makuri"},{"d":"2026-03-18","s":"run","m":53.1,"dist":6.62,"t":"Zwift - Mayan Bridge Loop in Watopia"},{"d":"2026-03-16","s":"bike","m":52.6,"dist":12.32,"t":"Zwift - Watopia s Waistband in Watopia"},{"d":"2026-03-15","s":"run","m":66.1,"dist":5.73,"t":"Zwift - 11.1 Ocean Blvd in Watopia"},{"d":"2026-03-13","s":"run","m":58.0,"dist":5.01,"t":"Zwift - Greater London Flat in London"},{"d":"2026-03-12","s":"run","m":53.4,"dist":4.51,"t":"Zwift - Chili Pepper in Watopia"},{"d":"2026-03-11","s":"run","m":31.0,"dist":2.78,"t":"New York Running"},{"d":"2026-03-03","s":"run","m":56.7,"dist":5.01,"t":"Zwift - Surfin  Safari in Watopia"},{"d":"2026-03-02","s":"run","m":57.8,"dist":5.01,"t":"Zwift - Chili Pepper in Watopia"},{"d":"2026-02-28","s":"run","m":47.0,"dist":2.62,"t":"Treadmill Running"},{"d":"2026-02-27","s":"run","m":36.1,"dist":3.01,"t":"Zwift - Castle Crit Run in Makuri Island"},{"d":"2026-02-17","s":"run","m":24.9,"dist":2.03,"t":"Zwift - Makuri 40 in Makuri Islands"},{"d":"2026-02-16","s":"run","m":50.4,"dist":5.01,"t":"Zwift - Farmland Loop in Makuri Islands"},{"d":"2026-02-15","s":"run","m":60.0,"dist":6.48,"t":"Treadmill Running"},{"d":"2026-01-15","s":"run","m":16.0,"dist":1.6,"t":"Zwift - Epic Run in Watopia"},{"d":"2026-01-14","s":"run","m":30.2,"dist":3.4,"t":"Treadmill Running"},{"d":"2026-01-13","s":"run","m":49.2,"dist":4.46,"t":"Zwift - Mountain Mash in Watopia"},{"d":"2026-01-12","s":"run","m":54.1,"dist":5.01,"t":"Zwift - Beach Island Loop in Watopia"},{"d":"2026-01-11","s":"bike","m":30.2,"dist":9.0,"t":"Indoor Cycling"},{"d":"2026-01-10","s":"run","m":55.9,"dist":5.01,"t":"Zwift - Park Perimeter Loop in New York"},{"d":"2026-01-09","s":"run","m":58.6,"dist":5.29,"t":"Zwift - City and the Sgurr in Scotland"},{"d":"2026-01-08","s":"run","m":56.9,"dist":5.01,"t":"Zwift - Island Hopper in Makuri Islands"},{"d":"2026-01-07","s":"run","m":58.8,"dist":5.01,"t":"Zwift - Mayan San Remo in Watopia"},{"d":"2026-01-06","s":"run","m":50.9,"dist":4.43,"t":"Zwift - Mayan Bridge Loop in Watopia"},{"d":"2026-01-05","s":"run","m":50.8,"dist":4.54,"t":"Zwift - 11.1 Ocean Blvd in Watopia"},{"d":"2026-01-04","s":"run","m":27.2,"dist":3.12,"t":"Zwift - Tour Of Tewit Well in Yorkshire"},{"d":"2026-01-03","s":"run","m":75.5,"dist":7.62,"t":"Long Run"},{"d":"2025-12-31","s":"bike","m":55.8,"dist":12.91,"t":"Zwift - Castle to Castle in Makuri Islan"},{"d":"2025-12-30","s":"swim","m":38.8,"dist":1725.0,"t":"Pool Swim"},{"d":"2025-12-30","s":"run","m":67.2,"dist":6.01,"t":"Zwift - Bridges and Boardwalks in Makuri"},{"d":"2025-12-28","s":"swim","m":38.4,"dist":1725.0,"t":"Pool Swim"},{"d":"2025-12-28","s":"run","m":57.2,"dist":5.0,"t":"Zwift - Temples and Towers in Makuri Isl"},{"d":"2025-12-26","s":"bike","m":52.6,"dist":14.82,"t":"Zwift - Southern Coast Cruise in Watopia"},{"d":"2025-12-26","s":"run","m":74.5,"dist":7.12,"t":"Zwift - London Loop in London"},{"d":"2025-12-24","s":"swim","m":40.4,"dist":1725.0,"t":"Pool Swim"},{"d":"2025-12-24","s":"bike","m":66.9,"dist":18.26,"t":"Zwift - Big Flat 8 in Watopia"},{"d":"2025-12-23","s":"run","m":56.7,"dist":5.53,"t":"Zwift - 5K Loop in Watopia"},{"d":"2025-12-19","s":"run","m":67.0,"dist":6.01,"t":"Zwift - Turf N Surf in Makuri Islands"},{"d":"2025-12-17","s":"run","m":66.2,"dist":6.01,"t":"Zwift - ZG25 Queen in Watopia"},{"d":"2025-12-15","s":"run","m":63.0,"dist":5.64,"t":"Zwift - London Calling in London"},{"d":"2025-12-13","s":"swim","m":39.5,"dist":1750.0,"t":"Pool Swim"},{"d":"2025-12-13","s":"run","m":67.8,"dist":6.01,"t":"Zwift - Greater London Flat in London"},{"d":"2025-12-12","s":"run","m":66.8,"dist":6.01,"t":"Zwift - Mayan Mash in Watopia"},{"d":"2025-12-11","s":"run","m":59.1,"dist":5.21,"t":"Zwift - The Highline in New York"},{"d":"2025-12-09","s":"run","m":56.9,"dist":5.01,"t":"Zwift - Temples and Towers in Makuri Isl"},{"d":"2025-12-08","s":"run","m":51.1,"dist":4.36,"t":"Zwift - Island Outskirts in Makuri Islan"},{"d":"2025-12-07","s":"swim","m":49.7,"dist":1776.0,"t":"Open Water Swimming"},{"d":"2025-12-06","s":"swim","m":34.2,"dist":1265.0,"t":"Open Water Swimming"},{"d":"2025-12-06","s":"run","m":54.1,"dist":4.88,"t":"Zwift - Mayan Bridge Loop in Watopia"},{"d":"2025-12-02","s":"run","m":42.1,"dist":3.68,"t":"Zwift - Greater London Flat in London"},{"d":"2025-11-30","s":"run","m":88.7,"dist":7.99,"t":"Bridgewater Running"},{"d":"2025-11-29","s":"run","m":42.0,"dist":4.25,"t":"Treadmill Running"},{"d":"2025-11-28","s":"run","m":78.8,"dist":7.36,"t":"Zwift - Makuri Madness in Makuri Islands"},{"d":"2025-11-26","s":"run","m":53.2,"dist":4.73,"t":"Zwift - Going Coastal in Watopia"},{"d":"2025-11-23","s":"run","m":46.8,"dist":4.33,"t":"Bridgewater Running"},{"d":"2025-11-21","s":"run","m":73.1,"dist":6.46,"t":"Washington Running"},{"d":"2025-11-20","s":"run","m":53.0,"dist":4.69,"t":"Washington Running"},{"d":"2025-11-18","s":"run","m":57.2,"dist":5.17,"t":"Zwift - 11.1 Ocean Blvd in Watopia"},{"d":"2025-11-16","s":"run","m":87.2,"dist":7.7,"t":"Bridgewater Running"},{"d":"2025-11-15","s":"run","m":83.3,"dist":7.68,"t":"Bridgewater Running"},{"d":"2025-11-11","s":"run","m":85.3,"dist":7.62,"t":"Bridgewater Running"},{"d":"2025-11-09","s":"run","m":157.1,"dist":13.16,"t":"HiTOPS Princeton Half Marathon (Virtual)"},{"d":"2025-11-07","s":"run","m":49.5,"dist":4.29,"t":"Zwift - Yoru Run in Makuri Islands"},{"d":"2025-11-05","s":"run","m":50.8,"dist":4.42,"t":"Zwift - Island Outskirts in Makuri Islan"},{"d":"2025-11-01","s":"run","m":82.3,"dist":7.55,"t":"Bridgewater Running"},{"d":"2025-10-30","s":"run","m":40.4,"dist":3.55,"t":"Edison Running"},{"d":"2025-10-29","s":"run","m":36.4,"dist":3.01,"t":"Zwift - Castle Crit Run in Makuri Island"},{"d":"2025-10-28","s":"run","m":28.9,"dist":2.83,"t":"New York Running"},{"d":"2025-10-27","s":"run","m":38.5,"dist":3.18,"t":"Zwift - 5K Loop in Watopia"},{"d":"2025-10-21","s":"run","m":30.3,"dist":2.58,"t":"Zwift - Temple Trek in Watopia"},{"d":"2025-10-19","s":"run","m":67.7,"dist":6.01,"t":"Zwift - Tour Of Tewit Well in Yorkshire"},{"d":"2025-10-18","s":"run","m":88.4,"dist":7.57,"t":"Bridgewater Running"},{"d":"2025-10-17","s":"run","m":34.0,"dist":2.83,"t":"Zwift - Fine and Sandy in Makuri Islands"},{"d":"2025-10-16","s":"run","m":9.1,"dist":1.01,"t":"Treadmill Running"},{"d":"2025-10-16","s":"run","m":36.3,"dist":3.54,"t":"Zwift - Sleepless City in Makuri Islands"},{"d":"2025-10-15","s":"bike","m":56.7,"dist":11.19,"t":"Zwift - Scotland Smash in Scotland"},{"d":"2025-10-14","s":"run","m":9.9,"dist":1.01,"t":"Treadmill Running"},{"d":"2025-10-14","s":"run","m":53.2,"dist":4.83,"t":"Zwift - Chili Pepper in Watopia"},{"d":"2025-10-13","s":"run","m":11.2,"dist":1.12,"t":"Treadmill Running"},{"d":"2025-10-13","s":"run","m":50.3,"dist":4.45,"t":"Zwift - Surfin  Safari in Watopia"},{"d":"2025-10-12","s":"run","m":47.3,"dist":4.08,"t":"Zwift - Temple Trek in Watopia"},{"d":"2025-10-11","s":"run","m":65.9,"dist":5.86,"t":"Bridgewater Running"},{"d":"2025-10-09","s":"run","m":59.2,"dist":5.06,"t":"Chicago Running"},{"d":"2025-10-08","s":"run","m":40.1,"dist":3.64,"t":"Chicago Running"},{"d":"2025-10-06","s":"run","m":46.2,"dist":3.99,"t":"Zwift - Bridges and Boardwalks in Makuri"},{"d":"2025-10-02","s":"run","m":43.0,"dist":3.57,"t":"Zwift - Croissant in France"},{"d":"2025-10-02","s":"run","m":41.5,"dist":4.02,"t":"Virtual Running"},{"d":"2025-09-29","s":"bike","m":52.9,"dist":14.15,"t":"Zwift - Greatest London Flat in London"},{"d":"2025-09-28","s":"run","m":48.1,"dist":4.07,"t":"Bridgewater Running"},{"d":"2025-09-27","s":"run","m":82.0,"dist":7.71,"t":"Bridgewater Running"},{"d":"2025-09-25","s":"run","m":43.4,"dist":3.68,"t":"Zwift - Outer Scotland in Scotland"},{"d":"2025-09-24","s":"run","m":29.6,"dist":2.82,"t":"New York Running"},{"d":"2025-09-23","s":"run","m":31.8,"dist":3.21,"t":"Treadmill Running"},{"d":"2025-09-23","s":"bike","m":70.0,"dist":14.3,"t":"Zwift - Knickerbocker Reverse in New Yor"},{"d":"2025-09-22","s":"run","m":79.7,"dist":7.24,"t":"Edison Running"},{"d":"2025-09-21","s":"run","m":51.4,"dist":4.22,"t":"Bridgewater Running"},{"d":"2025-09-20","s":"run","m":28.4,"dist":2.77,"t":"Treadmill Running"},{"d":"2025-09-18","s":"run","m":40.8,"dist":3.34,"t":"Zwift - Beach Island Loop in Watopia"},{"d":"2025-09-16","s":"run","m":37.9,"dist":3.11,"t":"Zwift - Deca Dash in Watopia"},{"d":"2025-09-15","s":"run","m":36.5,"dist":2.99,"t":"Zwift - Makuri Madness in Makuri Islands"},{"d":"2025-09-12","s":"run","m":37.6,"dist":3.04,"t":"Zwift - Suki s Playground in Makuri Isla"},{"d":"2025-09-11","s":"run","m":38.1,"dist":3.18,"t":"Zwift - Mayan Bridge Loop in Watopia"},{"d":"2025-09-07","s":"race","m":230.0,"dist":31.88,"t":"Finger Lakes Triathlon"},{"d":"2025-09-02","s":"run","m":53.6,"dist":4.62,"t":"Zwift - Makuri 40 in Makuri Islands"},{"d":"2025-09-01","s":"other","m":43.6,"dist":2.02,"t":"Edison Walking"},{"d":"2025-09-01","s":"swim","m":24.7,"dist":1000.0,"t":"Pool Swim"},{"d":"2025-09-01","s":"run","m":26.5,"dist":2.59,"t":"Treadmill Running"},{"d":"2025-09-01","s":"bike","m":86.8,"dist":20.76,"t":"Zwift - Makuri 40 in Makuri Islands"},{"d":"2025-08-30","s":"run","m":62.1,"dist":6.01,"t":"Treadmill Running"},{"d":"2025-08-30","s":"bike","m":83.0,"dist":25.0,"t":"Indoor Cycling"},{"d":"2025-08-30","s":"swim","m":43.3,"dist":1700.0,"t":"Pool Swim"},{"d":"2025-08-29","s":"run","m":13.6,"dist":1.48,"t":"Edison Running"},{"d":"2025-08-29","s":"run","m":44.9,"dist":4.39,"t":"Edison Running"},{"d":"2025-08-28","s":"run","m":38.1,"dist":3.16,"t":"Zwift - Greatest London Flat in London"},{"d":"2025-08-28","s":"bike","m":59.8,"dist":14.89,"t":"Zwift - Out And Back Again in Watopia"},{"d":"2025-08-27","s":"run","m":55.4,"dist":5.01,"t":"Zwift - Cobbled Climbs Run in Richmond"},{"d":"2025-08-27","s":"bike","m":44.0,"dist":10.26,"t":"Zwift - 2015 Worlds Course in Richmond"},{"d":"2025-08-26","s":"bike","m":45.3,"dist":12.07,"t":"Zwift - Turf N Surf in Makuri Islands"},{"d":"2025-08-26","s":"run","m":64.1,"dist":6.01,"t":"Zwift - Turf N Surf in Makuri Islands"},{"d":"2025-08-24","s":"other","m":16.1,"dist":0.76,"t":"Highlands Walking"},{"d":"2025-08-24","s":"bike","m":35.7,"dist":10.09,"t":"Zwift - Tempus Fugit in Watopia"},{"d":"2025-08-24","s":"run","m":54.8,"dist":5.01,"t":"Zwift - Flat Irons in New York"},{"d":"2025-08-23","s":"swim","m":39.9,"dist":1725.0,"t":"Pool Swim"},{"d":"2025-08-23","s":"bike","m":37.8,"dist":10.06,"t":"Zwift - Scotland Smash in Scotland"},{"d":"2025-08-23","s":"run","m":56.7,"dist":5.01,"t":"Zwift - Sleepless City in Makuri Islands"},{"d":"2025-08-22","s":"bike","m":43.4,"dist":11.68,"t":"Zwift - Suki s Playground in Makuri Isla"},{"d":"2025-08-22","s":"run","m":56.7,"dist":5.06,"t":"Zwift - Island Outskirts in Makuri Islan"},{"d":"2025-08-21","s":"run","m":52.8,"dist":4.62,"t":"Zwift - Greater London Flat in London"},{"d":"2025-08-20","s":"run","m":47.8,"dist":4.05,"t":"Zwift - Mayan 8 in Watopia"},{"d":"2025-08-19","s":"bike","m":31.8,"dist":10.0,"t":"Indoor Cycling"},{"d":"2025-08-19","s":"run","m":58.8,"dist":5.11,"t":"Zwift - Greatest London Loop in London"},{"d":"2025-08-18","s":"run","m":23.9,"dist":2.69,"t":"Zwift - Tair Dringfa Fechan in Watopia"},{"d":"2025-08-17","s":"swim","m":33.2,"dist":1450.0,"t":"Pool Swim"},{"d":"2025-08-17","s":"run","m":68.2,"dist":6.43,"t":"Zwift - Tides and Temples in Watopia"},{"d":"2025-08-16","s":"swim","m":12.7,"dist":525.0,"t":"Pool Swim"},{"d":"2025-08-15","s":"run","m":57.2,"dist":4.8,"t":"Alexandria Running"},{"d":"2025-08-14","s":"run","m":54.2,"dist":4.64,"t":"Alexandria Running"},{"d":"2025-08-12","s":"run","m":84.5,"dist":7.25,"t":"Alexandria Running"},{"d":"2025-08-11","s":"run","m":95.9,"dist":8.81,"t":"Alexandria Running"},{"d":"2025-08-08","s":"run","m":59.7,"dist":6.46,"t":"Zwift - Greater London Flat in London"},{"d":"2025-08-07","s":"run","m":51.5,"dist":5.04,"t":"Zwift - Chain Chomper in Makuri Islands"},{"d":"2025-08-06","s":"run","m":68.9,"dist":7.01,"t":"Zwift - Temples and Towers in Makuri Isl"},{"d":"2025-08-05","s":"run","m":8.2,"dist":0.77,"t":"Edison Running"},{"d":"2025-08-05","s":"bike","m":36.1,"dist":10.06,"t":"Zwift - Neon After Party in Makuri Islan"},{"d":"2025-08-05","s":"run","m":33.2,"dist":3.09,"t":"Zwift - Island Hopper in Makuri Islands"},{"d":"2025-08-04","s":"bike","m":35.9,"dist":10.06,"t":"Zwift - Makuri Madness in Makuri Islands"},{"d":"2025-08-04","s":"run","m":69.6,"dist":7.01,"t":"Zwift - Island Outskirts in Makuri Islan"},{"d":"2025-08-03","s":"swim","m":29.4,"dist":1225.0,"t":"Pool Swim"},{"d":"2025-08-03","s":"bike","m":38.5,"dist":12.0,"t":"Indoor Cycling"},{"d":"2025-08-03","s":"run","m":67.5,"dist":7.01,"t":"Zwift - Ocean Lava Cliffside Loop in Wat"},{"d":"2025-08-02","s":"swim","m":43.5,"dist":1725.0,"t":"Pool Swim"},{"d":"2025-08-02","s":"bike","m":37.1,"dist":12.0,"t":"Indoor Cycling"},{"d":"2025-08-02","s":"run","m":69.6,"dist":7.08,"t":"Zwift - Jon s Route in Watopia"},{"d":"2025-08-01","s":"run","m":60.1,"dist":6.08,"t":"Zwift - Mayan San Remo in Watopia"},{"d":"2025-07-31","s":"run","m":51.9,"dist":4.95,"t":"Zwift - 11.1 Ocean Blvd in Watopia"},{"d":"2025-07-30","s":"run","m":42.6,"dist":4.06,"t":"Zwift - Snowman in Watopia"},{"d":"2025-07-29","s":"run","m":54.2,"dist":5.28,"t":"Zwift - Road to Ruins in Watopia"},{"d":"2025-07-28","s":"run","m":35.1,"dist":3.29,"t":"Zwift - Tides and Temples in Watopia"},{"d":"2025-07-27","s":"swim","m":26.6,"dist":1050.0,"t":"Pool Swim"},{"d":"2025-07-27","s":"bike","m":40.0,"dist":12.0,"t":"Indoor Cycling"},{"d":"2025-07-27","s":"run","m":44.1,"dist":4.59,"t":"Treadmill Running"},{"d":"2025-07-26","s":"swim","m":45.0,"dist":1800.0,"t":"Pool Swim"},{"d":"2025-07-26","s":"bike","m":32.5,"dist":10.0,"t":"Indoor Cycling"},{"d":"2025-07-26","s":"run","m":69.5,"dist":7.01,"t":"Zwift - Ocean Lava Cliffside Loop in Wat"},{"d":"2025-07-25","s":"run","m":69.3,"dist":7.01,"t":"Zwift - 11.1 Ocean Blvd in Watopia"},{"d":"2025-07-24","s":"run","m":68.7,"dist":7.01,"t":"Zwift - Mayan Bridge Loop in Watopia"},{"d":"2025-07-21","s":"run","m":33.8,"dist":3.11,"t":"Zwift - Beach Island Loop in Watopia"},{"d":"2025-07-20","s":"swim","m":45.2,"dist":1725.0,"t":"Pool Swim"},{"d":"2025-07-20","s":"run","m":61.0,"dist":6.01,"t":"Zwift - Tides and Temples in Watopia"},{"d":"2025-07-19","s":"bike","m":30.0,"dist":10.0,"t":"Bike"},{"d":"2025-07-19","s":"swim","m":46.5,"dist":1750.0,"t":"Pool Swim"},{"d":"2025-07-19","s":"run","m":60.7,"dist":6.02,"t":"Zwift - Mayan Bridge Loop in Watopia"},{"d":"2025-07-18","s":"run","m":52.0,"dist":5.06,"t":"Zwift - Two Bridges Loop in Watopia"},{"d":"2025-07-16","s":"run","m":31.6,"dist":2.9,"t":"New York Running"},{"d":"2025-07-15","s":"run","m":22.5,"dist":2.01,"t":"Zwift - Temple Trek in Watopia"},{"d":"2025-07-14","s":"run","m":4.7,"dist":0.4,"t":"New York Running"},{"d":"2025-07-13","s":"swim","m":45.1,"dist":1925.0,"t":"Pool Swim"},{"d":"2025-07-12","s":"swim","m":41.0,"dist":1725.0,"t":"Pool Swim"},{"d":"2025-07-12","s":"bike","m":30.0,"dist":10.0,"t":"Bike 2/3"},{"d":"2025-07-12","s":"run","m":60.5,"dist":6.01,"t":"Zwift - Splash and Dash in Watopia"},{"d":"2025-07-11","s":"run","m":47.0,"dist":4.42,"t":"Zwift - 11.1 Ocean Blvd in Watopia"},{"d":"2025-07-10","s":"run","m":52.1,"dist":5.01,"t":"Zwift - Itza Party in Watopia"},{"d":"2025-07-09","s":"run","m":43.4,"dist":4.06,"t":"Zwift - Flat Route in Watopia"},{"d":"2025-07-08","s":"run","m":60.5,"dist":6.02,"t":"Zwift - Road to Sky in Watopia"},{"d":"2025-07-07","s":"run","m":43.7,"dist":4.07,"t":"Zwift - Canopies and Coastlines in Watop"},{"d":"2025-07-06","s":"bike","m":31.0,"dist":10.0,"t":"Sunday Pancakes 2/3 - Bike"},{"d":"2025-07-06","s":"swim","m":37.9,"dist":1700.0,"t":"Pool Swim"},{"d":"2025-07-06","s":"run","m":61.0,"dist":6.02,"t":"Zwift - Coast Crusher in Watopia"},{"d":"2025-07-05","s":"swim","m":36.4,"dist":1725.0,"t":"Pool Swim"},{"d":"2025-07-04","s":"swim","m":38.9,"dist":1775.0,"t":"Pool Swim"},{"d":"2025-07-04","s":"bike","m":33.0,"dist":10.0,"t":"Bike"},{"d":"2025-07-04","s":"run","m":36.1,"dist":3.28,"t":"Zwift - Temple Trek in Watopia"},{"d":"2025-07-03","s":"run","m":28.5,"dist":2.41,"t":"New York Running"},{"d":"2025-07-02","s":"run","m":29.8,"dist":3.01,"t":"New York Running"},{"d":"2025-07-01","s":"run","m":62.9,"dist":6.03,"t":"Zwift - Surfin  Safari in Watopia"},{"d":"2025-06-30","s":"run","m":61.1,"dist":6.01,"t":"Zwift - Beach Island Loop in Watopia"},{"d":"2025-06-29","s":"bike","m":35.0,"dist":10.0,"t":"Bike"},{"d":"2025-06-29","s":"swim","m":33.3,"dist":1275.0,"t":"Pool Swim"},{"d":"2025-06-29","s":"run","m":61.1,"dist":6.02,"t":"Zwift - Power to the Tower in Watopia"},{"d":"2025-06-28","s":"swim","m":32.2,"dist":1400.0,"t":"Pool Swim"},{"d":"2025-06-28","s":"run","m":43.5,"dist":4.0,"t":"Treadmill Running"},{"d":"2025-06-27","s":"run","m":61.8,"dist":6.01,"t":"Zwift - Temple Trek in Watopia"},{"d":"2025-06-26","s":"run","m":60.3,"dist":6.01,"t":"Zwift - Richmond Loop Around in Richmond"},{"d":"2025-06-25","s":"run","m":32.5,"dist":2.89,"t":"New York Running"},{"d":"2025-06-24","s":"run","m":51.9,"dist":5.01,"t":"Zwift - The Highline in New York"},{"d":"2025-06-23","s":"run","m":28.8,"dist":3.11,"t":"Zwift - Climber s Gambit in Watopia"},{"d":"2025-06-22","s":"swim","m":42.4,"dist":1700.0,"t":"Pool Swim"},{"d":"2025-06-22","s":"run","m":50.9,"dist":5.0,"t":"Zwift - BRAEk-fast Crits and Grits in Sc"},{"d":"2025-06-21","s":"swim","m":47.3,"dist":2075.0,"t":"Pool Swim"},{"d":"2025-06-21","s":"run","m":51.1,"dist":5.02,"t":"Zwift - The PRL Half in London"},{"d":"2025-06-20","s":"swim","m":29.2,"dist":1325.0,"t":"Pool Swim"},{"d":"2025-06-19","s":"swim","m":42.7,"dist":1600.0,"t":"Pool Swim"},{"d":"2025-06-19","s":"run","m":47.2,"dist":4.65,"t":"Zwift - Glyph Heights in Watopia"},{"d":"2025-06-18","s":"run","m":32.2,"dist":3.01,"t":"Zwift - Petit Boucle in France"},{"d":"2025-06-16","s":"run","m":32.7,"dist":3.08,"t":"Zwift - Park Perimeter Loop in New York"},{"d":"2025-06-10","s":"run","m":46.4,"dist":4.59,"t":"Zwift - Beach Island Loop in Watopia"},{"d":"2025-06-09","s":"run","m":27.8,"dist":2.71,"t":"New York Running"},{"d":"2025-06-08","s":"swim","m":36.8,"dist":1400.0,"t":"Pool Swim"},{"d":"2025-06-08","s":"run","m":60.8,"dist":6.01,"t":"Zwift - Mayan Bridge Loop in Watopia"},{"d":"2025-06-07","s":"swim","m":14.8,"dist":518.0,"t":"Open Water Swimming"},{"d":"2025-06-07","s":"run","m":61.5,"dist":6.02,"t":"Zwift - Beach Island Loop in Watopia"},{"d":"2025-06-06","s":"run","m":43.1,"dist":4.13,"t":"Zwift - Triple Twist in Watopia"},{"d":"2025-06-04","s":"run","m":30.8,"dist":2.72,"t":"New York Running"},{"d":"2025-06-03","s":"run","m":61.7,"dist":6.02,"t":"Zwift - Suki s Playground in Makuri Isla"},{"d":"2025-06-02","s":"run","m":61.1,"dist":5.98,"t":"Zwift - Sleepless City in Makuri Islands"},{"d":"2025-05-31","s":"run","m":66.9,"dist":6.0,"t":"Treadmill Running"},{"d":"2025-05-27","s":"run","m":34.3,"dist":3.23,"t":"New York Running"},{"d":"2025-05-26","s":"run","m":35.3,"dist":3.11,"t":"Zwift - Canopies and Coastlines in Watop"},{"d":"2025-05-25","s":"run","m":29.0,"dist":2.48,"t":"Treadmill Running"},{"d":"2025-05-24","s":"run","m":37.9,"dist":4.56,"t":"Treadmill Running"},{"d":"2025-05-23","s":"run","m":62.3,"dist":6.01,"t":"Zwift - Turf N Surf in Makuri Islands"},{"d":"2025-05-22","s":"run","m":32.7,"dist":3.0,"t":"Treadmill Running"},{"d":"2025-05-21","s":"run","m":57.1,"dist":5.48,"t":"Zwift - Mayan Mash in Watopia"},{"d":"2025-05-20","s":"run","m":46.7,"dist":4.22,"t":"Zwift - Flat Route in Watopia"},{"d":"2025-05-19","s":"run","m":45.7,"dist":4.18,"t":"Zwift - Flat Route in Watopia"},{"d":"2025-05-18","s":"run","m":62.5,"dist":6.02,"t":"Zwift - Shorelines and Summits in Watopi"},{"d":"2025-05-17","s":"run","m":66.9,"dist":6.09,"t":"Edison Running"},{"d":"2025-05-16","s":"run","m":48.8,"dist":4.28,"t":"Zwift - Peak Performance in Watopia"},{"d":"2025-05-12","s":"run","m":8.3,"dist":1.98,"t":"Treadmill Running"},{"d":"2025-05-11","s":"run","m":17.0,"dist":0.84,"t":"Treadmill Running"},{"d":"2025-05-10","s":"run","m":56.3,"dist":5.27,"t":"Zwift - Tour of Fire and Ice in Watopia"},{"d":"2025-05-09","s":"run","m":52.7,"dist":5.02,"t":"Zwift - Spiral into the Volcano in Watop"},{"d":"2025-05-08","s":"run","m":5.1,"dist":2.8,"t":"Treadmill Running"},{"d":"2025-05-07","s":"run","m":53.5,"dist":5.01,"t":"Zwift - London Uprising in London"},{"d":"2025-05-06","s":"run","m":54.5,"dist":5.01,"t":"Zwift - Danger Noodle in Watopia"},{"d":"2025-05-05","s":"run","m":53.4,"dist":5.02,"t":"Zwift - Shorelines and Summits in Watopi"},{"d":"2025-05-04","s":"run","m":62.7,"dist":4.51,"t":"Treadmill Running"},{"d":"2025-05-03","s":"run","m":4.2,"dist":0.36,"t":"Edison Running"},{"d":"2025-05-03","s":"other","m":37.3,"dist":1.57,"t":"Edison Walking"},{"d":"2025-05-02","s":"run","m":28.9,"dist":2.57,"t":"Zwift - Castle Crit Run in Makuri Island"},{"d":"2025-04-29","s":"run","m":85.5,"dist":6.98,"t":"Myrtle Beach Running"},{"d":"2025-04-28","s":"run","m":34.6,"dist":3.08,"t":"Myrtle Beach Running"},{"d":"2025-04-28","s":"run","m":17.1,"dist":1.37,"t":"Myrtle Beach Running"},{"d":"2025-04-27","s":"run","m":111.2,"dist":9.21,"t":"Myrtle Beach Running"},{"d":"2025-04-25","s":"bike","m":40.0,"dist":11.63,"t":"Zwift - Suki s Playground in Makuri Isla"},{"d":"2025-04-25","s":"run","m":29.1,"dist":2.52,"t":"Zwift - 5K Loop in Watopia"},{"d":"2025-04-24","s":"run","m":28.6,"dist":2.83,"t":"Treadmill Running"},{"d":"2025-04-23","s":"run","m":24.9,"dist":2.77,"t":"Treadmill Running"},{"d":"2025-04-22","s":"other","m":31.1,"dist":0.0,"t":"Elliptical"},{"d":"2025-04-22","s":"run","m":44.4,"dist":4.05,"t":"Zwift - That s Amore in Watopia"},{"d":"2025-04-21","s":"run","m":36.1,"dist":3.0,"t":"Treadmill Running"},{"d":"2025-04-19","s":"run","m":35.7,"dist":2.4,"t":"Treadmill Running"},{"d":"2025-04-17","s":"bike","m":54.9,"dist":15.38,"t":"Zwift - Turf N Surf in Makuri Islands"},{"d":"2025-04-17","s":"run","m":40.3,"dist":3.56,"t":"Zwift - Island Outskirts in Makuri Islan"},{"d":"2025-04-16","s":"run","m":43.6,"dist":3.55,"t":"Zwift - Bridges and Boardwalks in Makuri"},{"d":"2025-04-15","s":"run","m":16.5,"dist":1.31,"t":"Zwift - Farmland Loop in Makuri Islands"},{"d":"2025-04-14","s":"run","m":38.5,"dist":3.16,"t":"Bounce back 5K"},{"d":"2025-02-23","s":"run","m":19.8,"dist":1.79,"t":"Zwift - Two Bridges Loop in Watopia"},{"d":"2025-02-22","s":"run","m":70.3,"dist":7.02,"t":"Zwift - Mayan Bridge Loop in Watopia"},{"d":"2025-02-21","s":"run","m":30.1,"dist":2.65,"t":"Zwift - 11.1 Ocean Blvd in Watopia"},{"d":"2025-02-20","s":"run","m":58.5,"dist":5.5,"t":"Zwift - Temple Trek in Watopia"},{"d":"2025-02-19","s":"run","m":20.6,"dist":2.03,"t":"Zwift - Hudson Roll in New York"},{"d":"2025-02-18","s":"run","m":56.9,"dist":5.48,"t":"Zwift - Fine and Sandy in Makuri Islands"},{"d":"2025-02-15","s":"run","m":71.7,"dist":7.02,"t":"Zwift - Castle to Castle in Makuri Islan"},{"d":"2025-02-14","s":"run","m":52.8,"dist":5.03,"t":"Zwift - Island Hopper in Makuri Islands"},{"d":"2025-02-13","s":"other","m":45.2,"dist":3.05,"t":"Walking"},{"d":"2025-02-13","s":"run","m":48.1,"dist":5.02,"t":"Virtual Running"},{"d":"2025-02-13","s":"run","m":48.9,"dist":5.02,"t":"Zwift - Mayan Bridge Loop in Watopia"},{"d":"2025-02-12","s":"run","m":54.0,"dist":5.13,"t":"Zwift - Volcano Flat in Watopia"},{"d":"2025-02-10","s":"other","m":41.9,"dist":3.0,"t":"Walking"},{"d":"2025-02-10","s":"run","m":57.9,"dist":5.37,"t":"Zwift - Volcano Flat in Watopia"},{"d":"2025-02-09","s":"run","m":71.6,"dist":7.06,"t":"Zwift - Island Outskirts in Makuri Islan"},{"d":"2025-02-08","s":"run","m":30.2,"dist":2.65,"t":"Zwift - Island Outskirts in Makuri Islan"},{"d":"2025-02-07","s":"other","m":33.5,"dist":2.37,"t":"Walking"},{"d":"2025-02-07","s":"run","m":80.6,"dist":8.07,"t":"Zwift - Two Village Loop in Makuri Islan"},{"d":"2025-02-06","s":"run","m":69.8,"dist":6.69,"t":"Zwift - Lady Liberty in New York"},{"d":"2025-02-05","s":"run","m":53.3,"dist":5.02,"t":"Zwift - Beach Island Loop in Watopia"},{"d":"2025-02-05","s":"other","m":22.6,"dist":1.61,"t":"Walking"},{"d":"2025-02-04","s":"run","m":71.4,"dist":7.02,"t":"Zwift - 11.1 Ocean Blvd in Watopia"},{"d":"2025-02-03","s":"bike","m":12.2,"dist":3.42,"t":"Zwift - Mayan San Remo in Watopia"},{"d":"2025-02-03","s":"run","m":73.5,"dist":7.02,"t":"Zwift - Epic Run in Watopia"}]